mupy/__init__.py
mupy/assembly.py
mupy/coordinates.py
mupy/core.py
mupy/decode.py
mupy/hardware.py
mupy/viewport_coordinates.py
mupy/workspace.py
mupy/lib/README.md
mupy/lib/__init__.py
mupy/lib/BOLTX0004/LICENSE
mupy/lib/BOLTX0004/README.md
mupy/lib/BOLTX0004/__init__.py
mupy/lib/BOLTX0004/boltx0004.py
mupy/lib/BOLTX0004/scad/BOLTX0004.scad
mupy/lib/CRSPGR022/README.md
mupy/lib/CRSPGR022/__init__.py
mupy/lib/CRSPGR022/crspgr022.py
mupy/lib/CRSPGR022/scad/CRSPGR022.scad
mupy/lib/CUBX0006/LICENSE
mupy/lib/CUBX0006/README.md
mupy/lib/CUBX0006/__init__.py
mupy/lib/CUBX0006/cubx0006.py
mupy/lib/CUBX0006/scad/CUBX0006.scad
mupy/lib/CUBX0177/LICENSE
mupy/lib/CUBX0177/README.md
mupy/lib/CUBX0177/__init__.py
mupy/lib/CUBX0177/cubx0177.py
mupy/lib/CUBX0177/scad/CUBX0177.scad
mupy/lib/CUBX0188/LICENSE
mupy/lib/CUBX0188/cusbx0188.py
mupy/lib/CUBX0188/scad/CUBX0188.scad
mupy/lib/CUSBX0177/LICENSE
mupy/lib/CUSBX0177/cusbx0177.py
mupy/lib/CYLX0006/LICENSE
mupy/lib/CYLX0006/cylx0006.py
mupy/lib/CYLX0006/scad/CYLX0006.scad
mupy/lib/GEARX0005/README.md
mupy/lib/GEARX0005/__init__.py
mupy/lib/GEARX0005/crspgr022.py
mupy/lib/GEARX0005/scad/CRSPGR022.scad
mupy/lib/GEARX0005/scad/GEARX0005.scad
mupy/lib/HEXP0248/scad/HEXP0248.scad
mupy/mucli/__init__.py
mupy/mucli/input_branch.py
mupy/mucli/mucli.py
mupy/mucli/selection_branch.py
mupy-0.1.13.dist-info/LICENSE
mupy-0.1.13.dist-info/METADATA
mupy-0.1.13.dist-info/WHEEL
mupy-0.1.13.dist-info/top_level.txt
mupy-0.1.13.dist-info/RECORD
