Metadata-Version: 2.1
Name: mupy
Version: 0.1.13
Summary: Manufacturing Utility
Home-page: http://pypi.python.org/pypi/mupy/
Author: Michael Cranston Ryan
Author-email: spacetime.engineer@gmail.com
License: LICENSE.txt
Platform: UNKNOWN
Classifier: Intended Audience :: Education
Classifier: Intended Audience :: Manufacturing
Classifier: Intended Audience :: Science/Research
Classifier: Intended Audience :: End Users/Desktop
Classifier: Intended Audience :: Developers
Classifier: Intended Audience :: Other Audience
Classifier: License :: OSI Approved :: BSD License
Classifier: Programming Language :: Python :: 3.9
Classifier: Programming Language :: Other
License-File: LICENSE
